pcf8575/__init__.py
pcf8575-0.3.dist-info/LICENSE
pcf8575-0.3.dist-info/METADATA
pcf8575-0.3.dist-info/WHEEL
pcf8575-0.3.dist-info/top_level.txt
pcf8575-0.3.dist-info/RECORD
