Metadata-Version: 2.1
Name: pcf8575
Version: 0.3
Summary: Library for communication with PCF8575 IO expander over I2C
Home-page: https://github.com/rp3tya/PCF8575
Author: rp3tya
Author-email: rpetya@hotmail.com
License: UNKNOWN
Keywords: pcf8575 pcf8574 i2c i/o expander multiplexer
Platform: UNKNOWN
Classifier: Programming Language :: Python :: 3
Classifier: License :: OSI Approved :: MIT License
Classifier: Operating System :: OS Independent
Requires-Dist: smbus-cffi
